odoo10_addon_l10n_br_zip_correios-10.0.1.0.0.99.dev21-nspkg.pth
odoo/addons/l10n_br_zip_correios/README.rst
odoo/addons/l10n_br_zip_correios/__init__.py
odoo/addons/l10n_br_zip_correios/__manifest__.py
odoo/addons/l10n_br_zip_correios/i18n/l10n_br_zip_correios.pot
odoo/addons/l10n_br_zip_correios/models/__init__.py
odoo/addons/l10n_br_zip_correios/models/l10n_br_zip.py
odoo/addons/l10n_br_zip_correios/models/webservice_client.py
odoo/addons/l10n_br_zip_correios/static/description/icon.png
odoo/addons/l10n_br_zip_correios/tests/__init__.py
odoo/addons/l10n_br_zip_correios/tests/test_webservice_client.py
odoo10_addon_l10n_br_zip_correios-10.0.1.0.0.99.dev21.dist-info/METADATA
odoo10_addon_l10n_br_zip_correios-10.0.1.0.0.99.dev21.dist-info/WHEEL
odoo10_addon_l10n_br_zip_correios-10.0.1.0.0.99.dev21.dist-info/namespace_packages.txt
odoo10_addon_l10n_br_zip_correios-10.0.1.0.0.99.dev21.dist-info/top_level.txt
odoo10_addon_l10n_br_zip_correios-10.0.1.0.0.99.dev21.dist-info/RECORD
