Metadata-Version: 2.1
Name: odoo10-addon-l10n-br-zip-correios
Version: 10.0.1.0.0.99.dev21
Summary: Address from Brazilian Localization ZIP by Correios
Home-page: http://odoo-brasil.org
Author: KMEE, Odoo Community Association (OCA)
Author-email: support@odoo-community.org
License: AGPL-3
Platform: UNKNOWN
Classifier: Programming Language :: Python
Classifier: Framework :: Odoo
Classifier: License :: OSI Approved :: GNU Affero General Public License v3
Requires-Python: ~=2.7
Requires-Dist: odoo10-addon-l10n-br-zip
Requires-Dist: odoo (<10.1dev,>=10.0)
Requires-Dist: zeep
